PySlideShow/PySlideConfiguration.py
PySlideShow/PySlideRendering.py
PySlideShow/PySlideSlide.py
PySlideShow/PySlideSlideSequencer.py
PySlideShow/__init__.py
PySlideShow-0.0.4.data/scripts/PySlideShow.py
PySlideShow-0.0.4.dist-info/LICENSE
PySlideShow-0.0.4.dist-info/METADATA
PySlideShow-0.0.4.dist-info/WHEEL
PySlideShow-0.0.4.dist-info/top_level.txt
PySlideShow-0.0.4.dist-info/RECORD
